mdb/__init__.py
mdb/android/ADB.py
mdb/android/Android.py
mdb/android/DumpSysParser.py
mdb/android/__init__.py
mdb/builder/DeviceDetailBuilder.py
mdb/builder/__init__.py
mdb/core/CommandExecutor.py
mdb/core/MDB.py
mdb/core/Mobile.py
mdb/core/__init__.py
mdb/exceptions/ConnectedDevicesException.py
mdb/exceptions/UnsupportedPlatformException.py
mdb/exceptions/__init__.py
mdb/helpers/AndroidHelper.py
mdb/helpers/IOSHelper.py
mdb/helpers/__init__.py
mdb/ios/DumpsysParser.py
mdb/ios/IDB.py
mdb/ios/IOS.py
mdb/ios/__init__.py
mdb/utils/Commands.py
mdb/utils/__init__.py
monitor/__init__.py
monitor/builder/MonitoringDetailsBuilder.py
monitor/builder/__init__.py
monitor/clients/BuildsClient.py
monitor/clients/DeviceClient.py
monitor/clients/IntellisenseClient.py
monitor/clients/ScenariosClient.py
monitor/clients/__init__.py
monitor/constants/MongoDB.py
monitor/constants/__init__.py
monitor/entities/CpuData.py
monitor/entities/CrashData.py
monitor/entities/DeviceDetails.py
monitor/entities/ErrorResponse.py
monitor/entities/Intellisense.py
monitor/entities/MemoryData.py
monitor/entities/MongoService.py
monitor/entities/MonitoringDetails.py
monitor/entities/OptimusConfiguration.py
monitor/entities/RunConfiguration.py
monitor/entities/ScenarioTimeline.py
monitor/entities/ScreenshotStatistics.py
monitor/entities/SmartBOT.py
monitor/entities/TestCase.py
monitor/entities/TestFeedDetails.py
monitor/entities/__init__.py
monitor/entities/Device/DeviceType.py
monitor/entities/Device/Platform.py
monitor/entities/Device/Status.py
monitor/entities/Device/__init__.py
monitor/entities/performance/Activity.py
monitor/entities/performance/CpuStatistics.py
monitor/entities/performance/Exceptions.py
monitor/entities/performance/MemoryStatistics.py
monitor/entities/performance/ScreenshotStatistics.py
monitor/entities/performance/__init__.py
monitor/entities/reportParser/ExecutedScenario.py
monitor/entities/reportParser/Feature.py
monitor/entities/reportParser/Step.py
barbareeka_client_python-0.0.2.dist-info/METADATA
barbareeka_client_python-0.0.2.dist-info/WHEEL
barbareeka_client_python-0.0.2.dist-info/top_level.txt
barbareeka_client_python-0.0.2.dist-info/RECORD
